{"action0": "{\"_state\": \"left-click|1\", \"_action_id\": 0, \"_coords_list\": [{\"x\": 26, \"y\": 73}], \"_keyboard_buffer\": \"None\"}", "action1": "{\"_state\": \"left-click|1\", \"_action_id\": 1, \"_coords_list\": [{\"x\": 479, \"y\": 75}], \"_keyboard_buffer\": \"None\"}", "action2": "{\"_state\": \"left-click|1\", \"_action_id\": 2, \"_coords_list\": [{\"x\": 483, \"y\": 518}], \"_keyboard_buffer\": \"None\"}", "action3": "{\"_state\": \"left-click|1\", \"_action_id\": 3, \"_coords_list\": [{\"x\": 29, \"y\": 527}], \"_keyboard_buffer\": \"None\"}", "action4": "{\"_state\": \"left-click|1\", \"_action_id\": 4, \"_coords_list\": [{\"x\": 25, \"y\": 65}], \"_keyboard_buffer\": \"None\"}"}